{
  "db_name": "PostgreSQL",
  "query": "\n            INSERT INTO api_users_organizations (organization_id, api_user_id, role)\n            VALUES ($1, $2, $3)\n            ",
  "describe": {
    "columns": [],
    "parameters": {
      "Left": [
        "Uuid",
        "Uuid",
        {
          "Custom": {
            "name": "role",
            "kind": {
              "Enum": [
                "admin",
                "maintainer",
                "read_only"
              ]
            }
          }
        }
      ]
    },
    "nullable": []
  },
  "hash": "3d53ef166d9bc222bea1ac98d49e945cc2fc706c5b48955ba50da030726327e9"
}
