{
  "db_name": "PostgreSQL",
  "query": "\n            DELETE FROM api_keys\n            WHERE id = $1 AND organization_id = $2\n            RETURNING id\n            ",
  "describe": {
    "columns": [
      {
        "ordinal": 0,
        "name": "id",
        "type_info": "Uuid"
      }
    ],
    "parameters": {
      "Left": [
        "Uuid",
        "Uuid"
      ]
    },
    "nullable": [
      false
    ]
  },
  "hash": "959a864360acd922afa90cd1ff50c722f2dfb370cad41da253b9ee943fb2e13e"
}
