{
  "db_name": "PostgreSQL",
  "query": "\n            INSERT INTO api_users (id, email, github_user_id)\n            VALUES (gen_random_uuid(), $1, $2)\n            RETURNING id\n            ",
  "describe": {
    "columns": [
      {
        "ordinal": 0,
        "name": "id",
        "type_info": "Uuid"
      }
    ],
    "parameters": {
      "Left": [
        "Varchar",
        "Int8"
      ]
    },
    "nullable": [
      false
    ]
  },
  "hash": "c0a99cf45970bcdcc1c795f753d8135be3bd19eee13f23d0426e8ae44765060c"
}
