{
  "db_name": "PostgreSQL",
  "query": "\n            INSERT INTO projects (id, organization_id, name)\n            VALUES (gen_random_uuid(), $1, $2)\n            RETURNING *\n            ",
  "describe": {
    "columns": [
      {
        "ordinal": 0,
        "name": "id",
        "type_info": "Uuid"
      },
      {
        "ordinal": 1,
        "name": "organization_id",
        "type_info": "Uuid"
      },
      {
        "ordinal": 2,
        "name": "name",
        "type_info": "Varchar"
      },
      {
        "ordinal": 3,
        "name": "created_at",
        "type_info": "Timestamptz"
      },
      {
        "ordinal": 4,
        "name": "updated_at",
        "type_info": "Timestamptz"
      }
    ],
    "parameters": {
      "Left": [
        "Uuid",
        "Varchar"
      ]
    },
    "nullable": [
      false,
      false,
      false,
      false,
      false
    ]
  },
  "hash": "57d9a1e644c9243ceab7d33cb983480e0b8701de3f83c79d4959fc6d70df9790"
}
